example/__init__.py
flax/__init__.py
flax/generate_project.py
flaxx/__init__.py
flaxx/base.py
flaxx/enum_validator.py
flaxx/generate_project.py
flaxx/main.py
flaxx/pydantic_schema_generator.py
flaxx-0.0.3.dist-info/LICENSE
flaxx-0.0.3.dist-info/METADATA
flaxx-0.0.3.dist-info/WHEEL
flaxx-0.0.3.dist-info/top_level.txt
flaxx-0.0.3.dist-info/RECORD
