Metadata-Version: 2.1
Name: flaxx
Version: 0.0.3
Summary: A unified platform for data transmission and expression on the async Python stack and common mobile platforms for rapid, seamless, no-compromise development.
Home-page: https://github.com/timwford/flax
Author: Timothy Ford
Author-email: timefordrums@gmail.com
License: UNKNOWN
Platform: UNKNOWN
Classifier: Programming Language :: Python :: 3
Classifier: License :: OSI Approved :: MIT License
Classifier: Operating System :: OS Independent
Requires-Python: >=3.9
